timeout_executor/__init__.py
timeout_executor/const.py
timeout_executor/executor.py
timeout_executor/logging.py
timeout_executor/main.py
timeout_executor/py.typed
timeout_executor/result.py
timeout_executor/serde.py
timeout_executor/subprocess.py
timeout_executor/subprocess_jinja.py
timeout_executor/terminate.py
timeout_executor/types.py
timeout_executor-0.9.1.dist-info/METADATA
timeout_executor-0.9.1.dist-info/WHEEL
timeout_executor-0.9.1.dist-info/licenses/LICENSE
timeout_executor-0.9.1.dist-info/RECORD
