Metadata-Version: 2.3
Name: timeout-executor
Version: 0.9.1
Summary: execute with timeout
Project-URL: Repository, https://github.com/phi-friday/timeout-executor
Author-email: phi <phi.friday@gmail.com>
License: MIT License
License-File: LICENSE
Classifier: Development Status :: 4 - Beta
Classifier: Framework :: AnyIO
Classifier: Framework :: AsyncIO
Classifier: Framework :: Trio
Classifier: Programming Language :: Python :: 3
Classifier: Programming Language :: Python :: 3.9
Classifier: Programming Language :: Python :: 3.10
Classifier: Programming Language :: Python :: 3.11
Classifier: Programming Language :: Python :: 3.12
Classifier: Programming Language :: Python :: 3.13
Classifier: Programming Language :: Python :: Implementation :: CPython
Requires-Python: >=3.9
Requires-Dist: anyio>=4.0.0
Requires-Dist: async-wrapper>=0.9.0
Requires-Dist: cloudpickle>=3.0.0
Requires-Dist: exceptiongroup; python_version < '3.11'
Requires-Dist: psutil
Requires-Dist: tblib>=3.0.0
Requires-Dist: typing-extensions>=4.4.0
Provides-Extra: jinja
Requires-Dist: jinja2>=3.0.0; extra == 'jinja'
Provides-Extra: test
Requires-Dist: httpx>=0.27.2; extra == 'test'
Requires-Dist: pytest-cov>=5.0.0; extra == 'test'
Requires-Dist: pytest-xdist>=3.6.1; extra == 'test'
Requires-Dist: pytest>=8.0.2; extra == 'test'
Requires-Dist: trio>=0.24.0; extra == 'test'
Provides-Extra: uvloop
Requires-Dist: uvloop; (platform_system != 'Windows') and extra == 'uvloop'
